a_cv2_calculate_simlilarity/README.MD
a_cv2_calculate_simlilarity/__init__.py
a_cv2_calculate_simlilarity/requirements.txt
a_cv2_calculate_simlilarity/thirdparty.json
a_cv2_calculate_simlilarity-0.11.dist-info/LICENSE.rst
a_cv2_calculate_simlilarity-0.11.dist-info/METADATA
a_cv2_calculate_simlilarity-0.11.dist-info/WHEEL
a_cv2_calculate_simlilarity-0.11.dist-info/top_level.txt
a_cv2_calculate_simlilarity-0.11.dist-info/RECORD
