Metadata-Version: 2.1
Name: a-cv2-calculate-simlilarity
Version: 0.11
Summary: Calculate the simlilarity of 2 or more pictures with OpenCV
Home-page: https://github.com/hansalemaos/a_cv2_calculate_simlilarity
Author: Johannes Fischer
Author-email: aulasparticularesdealemaosp@gmail.com
License: MIT
Keywords: opencv,simlilarity,cv2
Classifier: Development Status :: 4 - Beta
Classifier: Programming Language :: Python :: 3 :: Only
Classifier: Programming Language :: Python :: 3.10
Classifier: Topic :: Software Development :: Libraries :: Python Modules
Classifier: Topic :: Utilities
License-File: LICENSE.rst
Requires-Dist: a-cv-imwrite-imread-plus
Requires-Dist: allescacher
Requires-Dist: numexpr
Requires-Dist: numpy
Requires-Dist: opencv-python
Requires-Dist: pandas
